tencentcloud/__init__.py
tencentcloud/ims/__init__.py
tencentcloud/ims/v20200713/__init__.py
tencentcloud/ims/v20200713/errorcodes.py
tencentcloud/ims/v20200713/ims_client.py
tencentcloud/ims/v20200713/ims_client_async.py
tencentcloud/ims/v20200713/models.py
tencentcloud/ims/v20201229/__init__.py
tencentcloud/ims/v20201229/errorcodes.py
tencentcloud/ims/v20201229/ims_client.py
tencentcloud/ims/v20201229/ims_client_async.py
tencentcloud/ims/v20201229/models.py
tencentcloud_sdk_python_ims-3.1.20.dist-info/METADATA
tencentcloud_sdk_python_ims-3.1.20.dist-info/WHEEL
tencentcloud_sdk_python_ims-3.1.20.dist-info/top_level.txt
tencentcloud_sdk_python_ims-3.1.20.dist-info/RECORD
